{"name":"BS Fire Emblem - Akaneia Senki Hen - Dai-4-wa - Hajimari no Toki (Japan) (4-28) (SoundLink)","description":"BS Fire Emblem - Akaneia Senki Hen - Dai-4-wa - Hajimari no Toki (Japan) (4-28) (SoundLink)","genre":"Strategy","developer":"Intelligent Systems","publisher":"Nintendo","franchise":"Fire Emblem","origin":"Japan","rom_name":"BS Fire Emblem - Akaneia Senki Hen - Dai-4-wa - Hajimari no Toki (Japan) (4-28) (SoundLink).bs","release_month":10,"release_year":1997,"size":1048576,"crc32":4123106436,"system":"Nintendo - Satellaview"}