{"name":"Kunio-kun no Dodge Ball Da yo Zenin Shuugou! - Tournament Special (Japan)","description":"Kunio-kun no Dodge Ball Da yo Zenin Shuugou! - Tournament Special (Japan)","genre":"Sports","developer":"Technos Japan","franchise":"River City Ransom / Kunio-kun","origin":"Japan","serial":"SHVC-ND","rom_name":"Kunio-kun no Dodge Ball Da yo Zenin Shuugou! - Tournament Special (Japan).sfc","release_month":8,"release_year":1993,"size":524288,"crc32":2993117037,"system":"Nintendo - Super Nintendo Entertainment System"}